netpath_resolver/__init__.py
netpath_resolver/netpath_resolver.py
netpath_resolver-0.3.0.dist-info/METADATA
netpath_resolver-0.3.0.dist-info/WHEEL
netpath_resolver-0.3.0.dist-info/RECORD
