Metadata-Version: 2.1
Name: netpath-resolver
Version: 0.3.0
Summary: 
Author: myuan
Author-email: zhengmy@ion.ac.cn
Requires-Python: >=3.8,<3.13
Classifier: Programming Language :: Python :: 3
Classifier: Programming Language :: Python :: 3.8
Classifier: Programming Language :: Python :: 3.9
Classifier: Programming Language :: Python :: 3.10
Classifier: Programming Language :: Python :: 3.11
Classifier: Programming Language :: Python :: 3.12
Requires-Dist: bidict (<1)
